CHANGELOG
LICENCE
MANIFEST.in
README.rst
setup.py
ItsAllGhosts.egg-info/PKG-INFO
ItsAllGhosts.egg-info/SOURCES.txt
ItsAllGhosts.egg-info/dependency_links.txt
ItsAllGhosts.egg-info/entry_points.txt
ItsAllGhosts.egg-info/not-zip-safe
ItsAllGhosts.egg-info/requires.txt
ItsAllGhosts.egg-info/top_level.txt
itsallghosts/__init__.py