Metadata-Version: 1.1
Name: ItsAllGhosts
Version: 0.3
Summary: UNKNOWN
Home-page: https://edugit.org/nik/itsallghosts
Author: Dominik George
Author-email: nik@naturalnet.de
License: UNKNOWN
Platform: UNKNOWN
Classifier: Development Status :: 4 - Beta
Classifier: Framework :: AsyncIO
Classifier: Intended Audience :: Developers
Classifier: Intended Audience :: End Users/Desktop
Classifier: License :: OSI Approved :: MIT License
Classifier: Operating System :: POSIX
Classifier: Programming Language :: Python :: 3 :: Only
Classifier: Topic :: Text Editors
